crc8.py
crc8-0.2.1.dist-info/LICENSE
crc8-0.2.1.dist-info/METADATA
crc8-0.2.1.dist-info/WHEEL
crc8-0.2.1.dist-info/top_level.txt
crc8-0.2.1.dist-info/zip-safe
crc8-0.2.1.dist-info/RECORD
