Metadata-Version: 2.1
Name: crc8
Version: 0.2.1
Summary: A module that implements the CRC8 hash algorithm for Python 2 and 3.
Home-page: https://github.com/niccokunzmann/crc8
Author: Nicco Kunzmann
Author-email: niccokunzmann@rambler.ru
License: MIT
Keywords: crc8 hash
Classifier: Intended Audience :: Developers
Classifier: License :: OSI Approved :: MIT License
Classifier: Topic :: Software Development :: Libraries :: Python Modules
Classifier: Topic :: Utilities
Classifier: Intended Audience :: Developers
Classifier: Natural Language :: English
Classifier: Operating System :: OS Independent
Classifier: Programming Language :: Python :: 2.6
Classifier: Programming Language :: Python :: 2.7
Classifier: Programming Language :: Python :: 3.3
Classifier: Programming Language :: Python :: 3.4
Classifier: Programming Language :: Python :: 3.5
Classifier: Development Status :: 5 - Production/Stable
License-File: LICENSE
